<!-- Tasker task by Connor Rhodes (connorrhodes.com)-->
<TaskerData sr="" dvi="1" tv="5.9.3">
	<Task sr="task3">
		<cdate>1600271052719</cdate>
		<edate>1600709544166</edate>
		<id>3</id>
		<nme>Switch Gvoice</nme>
		<pri>100</pri>
		<Action sr="act0" ve="7">
			<code>1646792910</code>
			<Bundle sr="arg0">
				<Vals sr="val">
					<com.twofortyfouram.locale.intent.extra.BLURB>Input Method: com.google.android.googlequicksearchbox/com.google.android.voicesearch.ime.VoiceInputMethodService</com.twofortyfouram.locale.intent.extra.BLURB>
					<com.twofortyfouram.locale.intent.extra.BLURB-type>java.lang.String</com.twofortyfouram.locale.intent.extra.BLURB-type>
					<net.dinglisch.android.tasker.JSON_ENCODED_KEYS>parameters</net.dinglisch.android.tasker.JSON_ENCODED_KEYS>
					<net.dinglisch.android.tasker.JSON_ENCODED_KEYS-type>java.lang.String</net.dinglisch.android.tasker.JSON_ENCODED_KEYS-type>
					<net.dinglisch.android.tasker.RELEVANT_VARIABLES>&lt;StringArray sr=""&gt;&lt;_array_net.dinglisch.android.tasker.RELEVANT_VARIABLES0&gt;%err
Error Code
Only available if you select &amp;lt;b&amp;gt;Continue Task After Error&amp;lt;/b&amp;gt; and the action ends in error&lt;/_array_net.dinglisch.android.tasker.RELEVANT_VARIABLES0&gt;&lt;_array_net.dinglisch.android.tasker.RELEVANT_VARIABLES1&gt;%errmsg
Error Message
Only available if you select &amp;lt;b&amp;gt;Continue Task After Error&amp;lt;/b&amp;gt; and the action ends in error&lt;/_array_net.dinglisch.android.tasker.RELEVANT_VARIABLES1&gt;&lt;/StringArray&gt;</net.dinglisch.android.tasker.RELEVANT_VARIABLES>
					<net.dinglisch.android.tasker.RELEVANT_VARIABLES-type>[Ljava.lang.String;</net.dinglisch.android.tasker.RELEVANT_VARIABLES-type>
					<net.dinglisch.android.tasker.extras.VARIABLE_REPLACE_KEYS>parameters plugininstanceid plugintypeid </net.dinglisch.android.tasker.extras.VARIABLE_REPLACE_KEYS>
					<net.dinglisch.android.tasker.extras.VARIABLE_REPLACE_KEYS-type>java.lang.String</net.dinglisch.android.tasker.extras.VARIABLE_REPLACE_KEYS-type>
					<net.dinglisch.android.tasker.subbundled>true</net.dinglisch.android.tasker.subbundled>
					<net.dinglisch.android.tasker.subbundled-type>java.lang.Boolean</net.dinglisch.android.tasker.subbundled-type>
					<parameters>{"inputServices":{"settingsAccessibilityServices":"","settingsChangeAccessibility":false,"settingsChangeNotificationListeners":false,"settingsChangeQuickSettingsTiles":false,"settingsInputMethod":"com.google.android.googlequicksearchbox/com.google.android.voicesearch.ime.VoiceInputMethodService","settingsNotificationListeners":"","settingsQuickSettingsTiles":""},"settingsCustom":{"customSettingRead":false},"settingsNotifications":{},"settingsRead":"","settingsScreen":{},"systemAnimations":{},"generatedValues":{}}</parameters>
					<parameters-type>java.lang.String</parameters-type>
					<plugininstanceid>03990b2d-4ca7-4f80-8bfd-0fb228d21dde</plugininstanceid>
					<plugininstanceid-type>java.lang.String</plugininstanceid-type>
					<plugintypeid>com.joaomgcd.autotools.intent.Intentsettings</plugintypeid>
					<plugintypeid-type>java.lang.String</plugintypeid-type>
				</Vals>
			</Bundle>
			<Str sr="arg1" ve="3">com.joaomgcd.autotools</Str>
			<Str sr="arg2" ve="3">com.joaomgcd.autotools.activity.ActivityConfigsettings</Str>
			<Int sr="arg3" val="60"/>
		</Action>
	</Task>
</TaskerData>
